gallicaGetter/__init__.py
gallicaGetter/context.py
gallicaGetter/contextSnippets.py
gallicaGetter/fetch.py
gallicaGetter/fullText.py
gallicaGetter/gallicaWrapper.py
gallicaGetter/issues.py
gallicaGetter/mostFrequent.py
gallicaGetter/pageText.py
gallicaGetter/pagination.py
gallicaGetter/papers.py
gallicaGetter/periodOccurrence.py
gallicaGetter/queries.py
gallicaGetter/volumeOccurrence.py
gallicaGetter/tests/__init__.py
gallicaGetter/tests/test_date.py
gallicaGetter/tests/test_dateGrouping.py
gallicaGetter/tests/test_gallicaWrapper.py
gallicaGetter/tests/test_gallicaXMLparse.py
gallicaGetter/tests/test_rows.py
gallicaGetter/tests/xmlForTesting/issues.xml
gallicaGetter/tests/xmlForTesting/occurrences.xml
gallicaGetter/tests/xmlForTesting/ocrText.xml
gallicaGetter/tests/xmlForTesting/papers.xml
gallicaGetter/utils/base_query_builds.py
gallicaGetter/utils/date.py
gallicaGetter/utils/index_query_builds.py
gallicaGetter/utils/parse_xml.py
gallicaGetter/utils/stopwordsEN.txt
gallicaGetter/utils/stopwordsFR.txt
gallicagetter-2.0.0.dist-info/METADATA
gallicagetter-2.0.0.dist-info/WHEEL
gallicagetter-2.0.0.dist-info/licenses/LICENSE
gallicagetter-2.0.0.dist-info/RECORD
