Metadata-Version: 2.1
Name: gallicaGetter
Version: 2.0.0
Summary: A collection of typed, async Python wrappers for the French National Library Gallica API.
Project-URL: Homepage, https://github.com/gleasonw/gallica-getter
Project-URL: Bug Tracker, https://github.com/gleasonw/gallica-getter/issues
Author-email: Will Gleason <wgleason9@gmail.com>
License-File: LICENSE
Classifier: License :: OSI Approved :: MIT License
Classifier: Operating System :: OS Independent
Classifier: Programming Language :: Python :: 3
Requires-Python: >=3.7
Requires-Dist: aiohttp==3.8.4
Requires-Dist: beautifulsoup4==4.12.0
Requires-Dist: lxml==4.9.2
Requires-Dist: pydantic==1.10.2
Requires-Dist: pytest==7.2.1
